spectralmatch/__init__.py
spectralmatch/__main__.py
spectralmatch/cli.py
spectralmatch/handlers.py
spectralmatch/statistics.py
spectralmatch/types_and_validation.py
spectralmatch/utils.py
spectralmatch/utils_multiprocessing.py
spectralmatch/mask/__init__.py
spectralmatch/mask/mask.py
spectralmatch/mask/utils_mask.py
spectralmatch/match/__init__.py
spectralmatch/match/global_regression.py
spectralmatch/match/local_block_adjustment.py
spectralmatch/seamline/__init__.py
spectralmatch/seamline/voronoi_center_seamline.py
spectralmatch-1.0.4.dist-info/licenses/LICENSE
spectralmatch-1.0.4.dist-info/METADATA
spectralmatch-1.0.4.dist-info/WHEEL
spectralmatch-1.0.4.dist-info/entry_points.txt
spectralmatch-1.0.4.dist-info/top_level.txt
spectralmatch-1.0.4.dist-info/RECORD
