Metadata-Version: 2.4
Name: spectralmatch
Version: 1.0.4
Summary: Global and local spectral matching of 2 or more overlapping rasters
Author-email: Kanoa Lindiwe <cankanoa@gmail.com>
Maintainer-email: Joseph Emile Honour Percival <ipercival@gmail.com>
License: MIT
Project-URL: Bug Tracker, https://github.com/cankanoa/spectralmatch
Project-URL: Source, https://github.com/cankanoa/spectralmatch
Keywords: histogram matching,spectral matching,image enhancement,remote sensing,geographic information systems(gis),radiometric correction,raster statistics,QGIS plugin,image normalization,contrast adjustment,satellite imagery,uas/drone imagery,multispectral,geospatial,raster transformation,digital image processing,environmental monitoring,seamlines,mosaicing
Classifier: Programming Language :: Python :: 3
Classifier: License :: OSI Approved :: MIT License
Classifier: Operating System :: OS Independent
Requires-Python: <3.13,>=3.9
License-File: LICENSE
Requires-Dist: ipython
Requires-Dist: numpy>=2.2.3
Requires-Dist: scipy>=1.15.2
Requires-Dist: fiona>=1.10.1
Requires-Dist: omnicloudmask>=1.0.11
Requires-Dist: geopandas>=1.0.1
Requires-Dist: scikit-image>=0.25.2
Requires-Dist: opencv-python>=4.11.0.86
Requires-Dist: fire>=0.7.0
Provides-Extra: system-level
Requires-Dist: gdal>=3.10.2; extra == "system-level"
Requires-Dist: proj>=9.3; extra == "system-level"
Requires-Dist: rasterio>=1.4.3; extra == "system-level"
Provides-Extra: dev
Requires-Dist: pytest>=7.0.0; extra == "dev"
Requires-Dist: pytest-mock>=3.14.0; extra == "dev"
Requires-Dist: pytest-cov>=4.0.0; extra == "dev"
Requires-Dist: flake8>=6.0.0; extra == "dev"
Requires-Dist: black>=23.0.0; extra == "dev"
Requires-Dist: pre-commit>=4.1.0; extra == "dev"
Provides-Extra: docs
Requires-Dist: mkdocs>=1.4.0; extra == "docs"
Requires-Dist: mkdocs-material>=9.0.0; extra == "docs"
Requires-Dist: mkdocs-jupyter>=0.24.0; extra == "docs"
Requires-Dist: mkdocstrings>=0.21.0; extra == "docs"
Requires-Dist: mkdocstrings-python>=0.10.0; extra == "docs"
Requires-Dist: mkdocs-git-revision-date-localized-plugin>=1.4.7; extra == "docs"
Requires-Dist: pymdown-extensions>=9.10; extra == "docs"
Requires-Dist: mkdocs-gen-files>=0.5.0; extra == "docs"
Provides-Extra: qgis-build
Requires-Dist: build; extra == "qgis-build"
Dynamic: license-file
